README.rst
setup.cfg
setup.py
classymail/__init__.py
classymail/base.py
classymail/mixins.py
classymail/utils.py
classymail/templatetags/__init__.py
classymail/templatetags/classymail_tags.py
django_classymail.egg-info/PKG-INFO
django_classymail.egg-info/SOURCES.txt
django_classymail.egg-info/dependency_links.txt
django_classymail.egg-info/requires.txt
django_classymail.egg-info/top_level.txt