Metadata-Version: 1.0
Name: django-classymail
Version: 0.2
Summary: E-mails in Django. Classy.
Home-page: UNKNOWN
Author: Rafal Stozek
Author-email: UNKNOWN
License: BSD
Platform: UNKNOWN
Classifier: Development Status :: 4 - Beta
Classifier: Framework :: Django
Classifier: Intended Audience :: Developers
Classifier: License :: OSI Approved :: BSD License
Classifier: Programming Language :: Python
Classifier: Programming Language :: Python :: 2.6
Classifier: Programming Language :: Python :: 2.7
